Metadata-Version: 1.0
Name: mtrx-calculation
Version: 0.1
Summary: Matrix calculation package
Home-page: UNKNOWN
Author: Toghrul Abilli
Author-email: togrulabilli@gmail.com
License: UNKNOWN
Platform: UNKNOWN
